ims/zip/__init__.py
ims/zip/adapters.py
ims/zip/configure.zcml
ims/zip/interfaces.py
ims/zip/permissions.py
ims/zip/testing.py
ims/zip/upgrades.py
ims/zip/zipper.py
ims/zip/browser/__init__.py
ims/zip/browser/configure.zcml
ims/zip/browser/unzipper.py
ims/zip/browser/zipper.py
ims/zip/browser/templates/unzipper.pt
ims/zip/browser/templates/zipper.pt
ims/zip/profiles/default/actions.xml
ims/zip/profiles/default/metadata.xml
ims/zip/profiles/default/registry.xml
ims/zip/profiles/uninstall/actions.xml
ims/zip/profiles/uninstall/registry.xml
ims/zip/profiles/upgrade_1/actions.xml
ims.zip-6.2.dist-info/METADATA
ims.zip-6.2.dist-info/WHEEL
ims.zip-6.2.dist-info/entry_points.txt
ims.zip-6.2.dist-info/RECORD
